bgc/__init__.py
bgc/__version__.py
bgc/core.py
bgc-0.0.1.dist-info/LICENSE
bgc-0.0.1.dist-info/METADATA
bgc-0.0.1.dist-info/WHEEL
bgc-0.0.1.dist-info/top_level.txt
bgc-0.0.1.dist-info/RECORD
