Metadata-Version: 2.1
Name: bgc
Version: 0.0.1
Summary: Biogeochemistry cycles
Home-page: https://github.com/xiejx5/bgc
Author: Cody Jame
Author-email: xiejx5@gmail.com
License: MIT
Classifier: License :: OSI Approved :: MIT License
Classifier: Programming Language :: Python
Classifier: Programming Language :: Python :: 3
Classifier: Programming Language :: Python :: 3.6
Classifier: Programming Language :: Python :: Implementation :: CPython
Classifier: Programming Language :: Python :: Implementation :: PyPy
Requires-Python: >=3.6.0
License-File: LICENSE
